storops/__init__.py
storops/exception.py
storops/connection/__init__.py
storops/connection/client.py
storops/connection/connector.py
storops/connection/exceptions.py
storops/lib/__init__.py
storops/lib/common.py
storops/lib/converter.py
storops/lib/ex_decorator_factory.py
storops/lib/job_helper.py
storops/lib/metric.py
storops/lib/models.py
storops/lib/parser.py
storops/lib/resource.py
storops/lib/version.py
storops/unity/__init__.py
storops/unity/calculator.py
storops/unity/client.py
storops/unity/enums.py
storops/unity/metric_configs.yaml
storops/unity/parser.py
storops/unity/parser_configs.yaml
storops/unity/resp.py
storops/unity/resource/__init__.py
storops/unity/resource/alert.py
storops/unity/resource/alert_config_snmp.py
storops/unity/resource/cg.py
storops/unity/resource/cifs_server.py
storops/unity/resource/cifs_share.py
storops/unity/resource/disk.py
storops/unity/resource/dns_server.py
storops/unity/resource/filesystem.py
storops/unity/resource/health.py
storops/unity/resource/host.py
storops/unity/resource/import_session.py
storops/unity/resource/interface.py
storops/unity/resource/job.py
storops/unity/resource/lun.py
storops/unity/resource/metric.py
storops/unity/resource/migration_object.py
storops/unity/resource/move_session.py
storops/unity/resource/nas_server.py
storops/unity/resource/nfs_server.py
storops/unity/resource/nfs_share.py
storops/unity/resource/pool.py
storops/unity/resource/port.py
storops/unity/resource/quota_config.py
storops/unity/resource/remote_interface.py
storops/unity/resource/remote_system.py
storops/unity/resource/replication_interface.py
storops/unity/resource/replication_session.py
storops/unity/resource/snap.py
storops/unity/resource/snap_schedule.py
storops/unity/resource/sp.py
storops/unity/resource/storage_resource.py
storops/unity/resource/system.py
storops/unity/resource/tenant.py
storops/unity/resource/tree_quota.py
storops/unity/resource/type_resource.py
storops/unity/resource/user_quota.py
storops-1.2.12.dist-info/licenses/LICENSE.txt
storops-1.2.12.dist-info/METADATA
storops-1.2.12.dist-info/WHEEL
storops-1.2.12.dist-info/top_level.txt
storops-1.2.12.dist-info/RECORD
