Metadata-Version: 2.4
Name: storops
Version: 1.2.12
Summary: Python API for VNX and Unity.
Home-page: https://github.com/emc-openstack/storops
Author: Cedric Zhuang
Author-email: cedric.zhuang@gmail.com
Maintainer: Dell EMC Unity OpenStack Team
Maintainer-email: spe.unity.openstack@emc.com
License: Apache Software License
Keywords: VNX,Unity,EMC,Storage
Platform: any
Classifier: Programming Language :: Python
Classifier: Programming Language :: Python :: 2.7
Classifier: Programming Language :: Python :: 3.4
Classifier: Programming Language :: Python :: 3.5
Classifier: Programming Language :: Python :: 3.6
Classifier: Programming Language :: Python :: 3.7
Classifier: Programming Language :: Python :: 3.8
Classifier: Programming Language :: Python :: 3.9
Classifier: Programming Language :: Python :: 3.10
Classifier: Natural Language :: English
Classifier: Intended Audience :: Developers
Classifier: Operating System :: OS Independent
Classifier: Development Status :: 5 - Production/Stable
Classifier: Topic :: Software Development :: Libraries
Classifier: Topic :: Utilities
Classifier: License :: OSI Approved :: Apache Software License
Requires-Python: >=2.7, !=3.0.*, !=3.1.*, !=3.2.*, !=3.3.*
License-File: LICENSE.txt
Requires-Dist: requests>=2.32.4
Requires-Dist: PyYAML>=6.0.2
Requires-Dist: six>=1.9.0
Requires-Dist: enum34
Requires-Dist: python-dateutil>=2.4.2
Requires-Dist: retryz>=0.1.8
Requires-Dist: cachez>=0.1.0
Requires-Dist: bitmath>=1.3.0
Requires-Dist: urllib3>=2.5.0
Dynamic: author
Dynamic: author-email
Dynamic: classifier
Dynamic: description
Dynamic: home-page
Dynamic: keywords
Dynamic: license
Dynamic: license-file
Dynamic: maintainer
Dynamic: maintainer-email
Dynamic: platform
Dynamic: requires-dist
Dynamic: requires-python
Dynamic: summary
